tempodb_archive.py
tempodb_archive-1.0.0.dist-info/DESCRIPTION.rst
tempodb_archive-1.0.0.dist-info/entry_points.txt
tempodb_archive-1.0.0.dist-info/METADATA
tempodb_archive-1.0.0.dist-info/metadata.json
tempodb_archive-1.0.0.dist-info/RECORD
tempodb_archive-1.0.0.dist-info/top_level.txt
tempodb_archive-1.0.0.dist-info/WHEEL
