Metadata-Version: 2.0
Name: tempodb-archive
Version: 1.0.0
Summary: Archive TempoDB Datapoints
Home-page: https://github.com/eman/tempodb-archive
Author: Emmanuel Levijarvi
Author-email: emansl@gmail.com
License: BSD
Keywords: tempodb archive
Platform: UNKNOWN
Classifier: Development Status :: 4 - Beta
Classifier: Intended Audience :: Developers
Classifier: Topic :: Utilities
Classifier: License :: OSI Approved :: BSD License
Classifier: Operating System :: OS Independent
Classifier: Programming Language :: Python :: 2.7
Requires-Dist: tempodb
